software/smartfusion/hdl/stonyman_controller.v
////////////////////////////////////////////////////////////////////////////////
// Company: University of Michigan
//
// File: stonyman_controller.v
//
// Description:
//      Controller for the CentEye Stonyman imager.
//      Note: the on-chip amplifier is slow and this code does not use it
//
// Targeted device: <Family::SmartFusion> <Die::A2F500M3G> <Package::484 FBGA>
// Author: Branden Ghena
//
////////////////////////////////////////////////////////////////////////////////

// Stonyman definitions
`define COLSEL_PTR 0
`define ROWSEL_PTR 1
`define VSW_PTR    2
`define HSW_PTR    3
`define VREF_PTR   4
`define CONFIG_PTR 5
`define NBIAS_PTR  6
`define AOBIAS_PTR 7
`define ROW_RESOLUTION 112
`define COL_RESOLUTION 112

// State definitions
`define INIT_RESET  0
`define INIT_PTR    1
`define INIT_COL    2
`define INIT_ROW    3
`define INIT_VSW    4
`define INIT_HSW    5
`define INIT_VREF   6
`define INIT_NBIAS  7
`define INIT_AOBIAS 8
`define INIT_CONFIG 9
`define IDLE        10
`define CAPTURE     11
`define STATE_BITS 4

`define START 0
`define WAIT  1
`define PIN_STATE_BITS 1

`define SET_PTR   0
`define RESET_VAL 1
`define SET_VAL   2

`define SET_ROW_PTR 0
`define SET_ROW_VAL 1
`define SET_COL_PTR 2
`define SET_COL_VAL 3
`define WAIT_ADC    4

// Timing definitions
//TODO: define me based on clock and nanoseconds...
//`define COUNTS_PIN_HIGH 100
//`define TIMER_BITS 8


module stonyman (
    input wire clk,
    input wire reset,

    // Control signals
    input wire frame_capture_start,
    input wire adc_capture_done,

    // Timing
    //input wire [7:0] pulse_counts,

    // Register settings
    //  settings are configured by the user through a kernel ioctl, but are
    //  only read on reset
    input wire [7:0] vsw_value,
    input wire [7:0] hsw_value,
    input wire [5:0] vref_value,
    input wire [5:0] config_value,
    input wire [5:0] nbias_value,
    input wire [5:0] aobias_value,

    // Frame mask input
    input wire mask_capture_pixel,

    // Status signals
    output reg controller_busy,
    output reg frame_capture_done,
    output reg adc_capture_start,

    // Digital control lines
    output reg resp,
    output reg incp,
    output reg resv,
    output reg incv,
    output reg inphi,

    // Frame mask address
    output reg [6:0] mask_pixel_row,
    output reg [6:0] mask_pixel_col,
    //output reg [3:0] main_state

    //Line sampled completely (for adc_controller -> pupil_detect)
    output reg newline_sample

    );

    // State registers
    reg [`STATE_BITS-1:0] main_state;
    reg [`STATE_BITS-1:0] main_state_nxt;
    reg [`STATE_BITS-1:0] sub_state;
    reg [`STATE_BITS-1:0] sub_state_nxt;
    reg [`PIN_STATE_BITS-1:0] pulse_pin_state;
    reg [`PIN_STATE_BITS-1:0] pulse_pin_state_nxt;

    // Frame mask signals
    reg [6:0] mask_pixel_row_nxt;
    reg [6:0] mask_pixel_col_nxt;

    // Stonyman model
    reg [2:0] ptr_value;
    reg [2:0] ptr_value_nxt;
    reg [7:0] reg_value [7:0];
    reg [7:0] reg_value_nxt [7:0];

    // Register thine outputs
    reg frame_capture_done_nxt;
    reg adc_capture_start_nxt;
    reg resp_nxt;
    reg incp_nxt;
    reg resv_nxt;
    reg incv_nxt;
    reg inphi_nxt;

    // Signal Error task
    task SIGNAL_ERROR;
    begin
        // Set output signals so that the error can be probed and narowed down
        resp_nxt  = main_state[0];
        incp_nxt  = main_state[1];
        resv_nxt  = main_state[2];
        incv_nxt  = sub_state[0];
        inphi_nxt = sub_state[1];
    end
    endtask

    // Pulse Pin task
    task PULSE_PIN;
        input  [`STATE_BITS-1:0] cur_state;
        input  [`STATE_BITS-1:0] new_state;
        output [`STATE_BITS-1:0] state_nxt;
        output pin;
    begin
        case (pulse_pin_state)
            `START: begin
                // Begin pulse
                pin = 1;
                pulse_pin_state_nxt = `WAIT;
                state_nxt = cur_state;
            end
            `WAIT: begin
                // Pulse complete
                pin = 0;
                pulse_pin_state_nxt = `START;
                state_nxt = new_state;
            end
            default: begin
                // Something has gone wrong
                SIGNAL_ERROR();
            end
        endcase
    end
    endtask

    // Reset Pointer task
    task RESET_PTR;
        input  [`STATE_BITS-1:0] cur_state;
        input  [`STATE_BITS-1:0] new_state;
        output [`STATE_BITS-1:0] state_nxt;
    begin
        PULSE_PIN(cur_state, new_state, state_nxt, resp_nxt);
        if (state_nxt != cur_state) begin
            ptr_value_nxt = 0;
        end
    end
    endtask

    // Reset Value task
    task RESET_VAL;
        input  [`STATE_BITS-1:0] cur_state;
        input  [`STATE_BITS-1:0] new_state;
        output [`STATE_BITS-1:0] state_nxt;
    begin
        PULSE_PIN(cur_state, new_state, state_nxt, resv_nxt);
        if (state_nxt != cur_state) begin
            reg_value_nxt[ptr_value] = 0;
        end
    end
    endtask

    // Increment Pointer task
    task INCR_PTR;
        input  [`STATE_BITS-1:0] cur_state;
        input  [`STATE_BITS-1:0] new_state;
        output [`STATE_BITS-1:0] state_nxt;
    begin
        PULSE_PIN(cur_state, new_state, state_nxt, incp_nxt);
        if (state_nxt != cur_state) begin
            ptr_value_nxt = ptr_value+1;
        end
    end
    endtask

    // Increment Value task
    task INCR_VAL;
        input  [`STATE_BITS-1:0] cur_state;
        input  [`STATE_BITS-1:0] new_state;
        output [`STATE_BITS-1:0] state_nxt;
    begin
        PULSE_PIN(cur_state, new_state, state_nxt, incv_nxt);
        if (state_nxt != cur_state) begin
            reg_value_nxt[ptr_value] = reg_value[ptr_value]+1;
        end
    end
    endtask

    // Set Pointer task
    task SET_PTR;
        input  [2:0] new_ptr_val;
        input  [`STATE_BITS-1:0] cur_state;
        input  [`STATE_BITS-1:0] new_state;
        output [`STATE_BITS-1:0] state_nxt;
    begin
        if (ptr_value < new_ptr_val) begin
            // Increment the ptr
            INCR_PTR(cur_state, new_state, state_nxt);
        end else if (ptr_value > new_ptr_val) begin
            // Ptr needs to be reset, this will automatically transition us to
            //  incrementing the ptr
            RESET_PTR(cur_state, new_state, state_nxt);
        end else begin
            // They are already equal!
            ptr_value_nxt = ptr_value;
            state_nxt = new_state;
        end

        // Don't exit SET_PTR until we reach the desired value
        if (ptr_value_nxt != new_ptr_val) begin
            state_nxt = cur_state;
        end
    end
    endtask

    // Set Value task
    task SET_VAL;
        input  [7:0] new_reg_val;
        input  [`STATE_BITS-1:0] cur_state;
        input  [`STATE_BITS-1:0] new_state;
        output [`STATE_BITS-1:0] state_nxt;
    begin
        if (reg_value[ptr_value] < new_reg_val) begin
            // Increment the val
            INCR_VAL(cur_state, new_state, state_nxt);
            state_nxt = cur_state;
        end else begin
            // They are already equal!
            reg_value_nxt[ptr_value] = reg_value[ptr_value];
            state_nxt = new_state;
        end
    end
    endtask

    // Goto Value task
    //  This task can reset the Value, while SET_VAL cannot
    task GOTO_VAL;
        input  [7:0] new_reg_val;
        input  [`STATE_BITS-1:0] cur_state;
        input  [`STATE_BITS-1:0] new_state;
        output [`STATE_BITS-1:0] state_nxt;
    begin
        if (reg_value[ptr_value] < new_reg_val) begin
            // Increment the val
            INCR_VAL(cur_state, new_state, state_nxt);
        end else if (reg_value[ptr_value] > new_reg_val) begin
            // Val needs to be reset, this will automatically transition us to
            //  incrementing the val
            RESET_VAL(cur_state, new_state, state_nxt);
        end else begin
            // They are already equal!
            reg_value_nxt[ptr_value] = reg_value[ptr_value];
            state_nxt = new_state;
        end

        // Don't exit GOTO_VAL until we reach the desired value
        if (reg_value_nxt[ptr_value] != new_reg_val) begin
            state_nxt = cur_state;
        end
    end
    endtask

    // Next Pixel task
    task NEXT_PIXEL;
    begin
        if (reg_value_nxt[`COLSEL_PTR] < (`COL_RESOLUTION-1)) begin
            // Continue iterating across the row
            mask_pixel_col_nxt = mask_pixel_col+1;
            sub_state_nxt = `SET_COL_VAL;
            //still iterating across row
            newline_sample = 0;
        end else begin
            if (reg_value_nxt[`ROWSEL_PTR] < (`ROW_RESOLUTION-1)) begin
                // Move to next row
                mask_pixel_col_nxt = 0;
                mask_pixel_row_nxt = mask_pixel_row+1;
                sub_state_nxt = `SET_ROW_PTR;
                //newline being sampled
                newline_sample = 1;
            end else begin
                // Finished!
                mask_pixel_col_nxt = 0;
                mask_pixel_row_nxt = 0;
                main_state_nxt = `IDLE;
                frame_capture_done_nxt = 1;
                //done so no new line
                newline_sample = 0;
            end
        end
    end
    endtask

    always @(*) begin
        main_state_nxt = main_state;
        sub_state_nxt  = sub_state;
        pulse_pin_state_nxt = pulse_pin_state;

        mask_pixel_row_nxt = mask_pixel_row;
        mask_pixel_col_nxt = mask_pixel_col;

        ptr_value_nxt = ptr_value;
        reg_value_nxt[0] = reg_value[0];
        reg_value_nxt[1] = reg_value[1];
        reg_value_nxt[2] = reg_value[2];
        reg_value_nxt[3] = reg_value[3];
        reg_value_nxt[4] = reg_value[4];
        reg_value_nxt[5] = reg_value[5];
        reg_value_nxt[6] = reg_value[6];
        reg_value_nxt[7] = reg_value[7];

        frame_capture_done_nxt = 0;
        adc_capture_start_nxt  = 0;
        resp_nxt  = 0;
        incp_nxt  = 0;
        resv_nxt  = 0;
        incv_nxt  = 0;
        inphi_nxt = 0;

        controller_busy = (main_state != `IDLE);

        case (main_state)
            `INIT_RESET: begin
                // Do nothing until we are out of reset
                main_state_nxt = `INIT_PTR;
            end
            `INIT_PTR: begin
                RESET_PTR(`INIT_PTR, `INIT_COL, main_state_nxt);
            end
            `INIT_COL: begin
                case (sub_state)
                    `SET_PTR:   SET_PTR(`COLSEL_PTR, `SET_PTR, `RESET_VAL, sub_state_nxt);
                    `RESET_VAL: RESET_VAL(`INIT_COL, `INIT_ROW, main_state_nxt);
                endcase
            end
            `INIT_ROW: begin
                case (sub_state)
                    `SET_PTR:   SET_PTR(`ROWSEL_PTR, `SET_PTR, `RESET_VAL, sub_state_nxt);
                    `RESET_VAL: RESET_VAL(`INIT_ROW, `INIT_VSW, main_state_nxt);
                endcase
            end
            `INIT_VSW: begin
                case (sub_state)
                    `SET_PTR:   SET_PTR(`VSW_PTR, `SET_PTR, `RESET_VAL, sub_state_nxt);
                    `RESET_VAL: RESET_VAL(`RESET_VAL, `SET_VAL, sub_state_nxt);
                    `SET_VAL:   SET_VAL(vsw_value, `INIT_VSW, `INIT_HSW, main_state_nxt);
                endcase
            end
            `INIT_HSW: begin
                case (sub_state)
                    `SET_PTR:   SET_PTR(`HSW_PTR, `SET_PTR, `RESET_VAL, sub_state_nxt);
                    `RESET_VAL: RESET_VAL(`RESET_VAL, `SET_VAL, sub_state_nxt);
                    `SET_VAL:   SET_VAL(hsw_value, `INIT_HSW, `INIT_VREF, main_state_nxt);
                endcase
            end
            `INIT_VREF: begin
                case (sub_state)
                    `SET_PTR:   SET_PTR(`VREF_PTR, `SET_PTR, `RESET_VAL, sub_state_nxt);
                    `RESET_VAL: RESET_VAL(`RESET_VAL, `SET_VAL, sub_state_nxt);
                    `SET_VAL:   SET_VAL(vref_value, `INIT_VREF, `INIT_NBIAS, main_state_nxt);
                endcase
            end
            `INIT_NBIAS: begin
                case (sub_state)
                    `SET_PTR:   SET_PTR(`NBIAS_PTR, `SET_PTR, `RESET_VAL, sub_state_nxt);
                    `RESET_VAL: RESET_VAL(`RESET_VAL, `SET_VAL, sub_state_nxt);
                    `SET_VAL:   SET_VAL(nbias_value, `INIT_NBIAS, `INIT_AOBIAS, main_state_nxt);
                endcase
            end
            `INIT_AOBIAS: begin
                case (sub_state)
                    `SET_PTR:   SET_PTR(`AOBIAS_PTR, `SET_PTR, `RESET_VAL, sub_state_nxt);
                    `RESET_VAL: RESET_VAL(`RESET_VAL, `SET_VAL, sub_state_nxt);
                    `SET_VAL:   SET_VAL(aobias_value, `INIT_AOBIAS, `INIT_CONFIG, main_state_nxt);
                endcase
            end
            `INIT_CONFIG: begin
                case (sub_state)
                    `SET_PTR:   SET_PTR(`CONFIG_PTR, `SET_PTR, `RESET_VAL, sub_state_nxt);
                    `RESET_VAL: RESET_VAL(`RESET_VAL, `SET_VAL, sub_state_nxt);
                    `SET_VAL:   SET_VAL(config_value, `INIT_CONFIG, `IDLE, main_state_nxt);
                endcase
            end
            `IDLE: begin
                if (frame_capture_start) begin
                    mask_pixel_col_nxt = 0;
                    mask_pixel_row_nxt = 0;
                    main_state_nxt = `CAPTURE;
                end else begin
                    frame_capture_done_nxt = 0;
                    main_state_nxt = `IDLE;
                end
            end
            `CAPTURE: begin
                case (sub_state)
                    `SET_ROW_PTR: SET_PTR(`ROWSEL_PTR, `SET_ROW_PTR, `SET_ROW_VAL, sub_state_nxt);
                    `SET_ROW_VAL: GOTO_VAL(mask_pixel_row, `SET_ROW_VAL, `SET_COL_PTR, sub_state_nxt);
                    `SET_COL_PTR: SET_PTR(`COLSEL_PTR, `SET_COL_PTR, `SET_COL_VAL, sub_state_nxt);
                    `SET_COL_VAL: begin
                        GOTO_VAL(mask_pixel_col, `SET_COL_VAL, `WAIT_ADC, sub_state_nxt);
                        if (sub_state_nxt == `WAIT_ADC) begin
                            if (mask_capture_pixel) begin
                                // Signal ADC to being capture
                                adc_capture_start_nxt = 1;
                            end else begin
                                // This pixel doesn't need to be captured,
                                //  move on
                                NEXT_PIXEL();
                            end
                        end
                    end
                    `WAIT_ADC: begin
                        // Wait until the ADC has captured the data
                        //  If the FIFO is full, the ADC will stall and so
                        //      will we
                        adc_capture_start_nxt = 0;
                        if (adc_capture_done) begin
                            // Completed ADC capture, go to next pixel
                            NEXT_PIXEL();
                        end
                    end
                    default: begin
                        // Something has gone wrong
                        SIGNAL_ERROR();
                    end
                endcase
            end
            default: begin
                // Something has gone wrong
                SIGNAL_ERROR();
            end
        endcase

        // Since tasks just move us from state to state, substate needs to be
        //  reset automatically
        if (main_state != main_state_nxt) begin
            sub_state_nxt = 0;
        end
    end

    always @(posedge clk or posedge reset) begin
        if (reset) begin
            // Initialize states
            main_state      <= `INIT_RESET;
            sub_state       <= 0;
            pulse_pin_state <= `START;

            frame_capture_done <= 0;
            adc_capture_start  <= 0;
            resp  <= 0;
            incp  <= 0;
            resv  <= 0;
            incv  <= 0;
            inphi <= 0;

            mask_pixel_row <= 0;
            mask_pixel_col <= 0;

            ptr_value <= 0;
            reg_value[0] <= 0;
            reg_value[1] <= 0;
            reg_value[2] <= 0;
            reg_value[3] <= 0;
            reg_value[4] <= 0;
            reg_value[5] <= 0;
            reg_value[6] <= 0;
            reg_value[7] <= 0;

            newline_sample = 0;
        end else begin
            // Update states
            main_state      <= main_state_nxt;
            sub_state       <= sub_state_nxt;
            pulse_pin_state <= pulse_pin_state_nxt;

            frame_capture_done <= frame_capture_done_nxt;
            adc_capture_start  <= adc_capture_start_nxt;
            resp  <= resp_nxt;
            incp  <= incp_nxt;
            resv  <= resv_nxt;
            incv  <= incv_nxt;
            inphi <= inphi_nxt;

            mask_pixel_row <= mask_pixel_row_nxt;
            mask_pixel_col <= mask_pixel_col_nxt;

            ptr_value <= ptr_value_nxt;
            reg_value[0] <= reg_value_nxt[0];
            reg_value[1] <= reg_value_nxt[1];
            reg_value[2] <= reg_value_nxt[2];
            reg_value[3] <= reg_value_nxt[3];
            reg_value[4] <= reg_value_nxt[4];
            reg_value[5] <= reg_value_nxt[5];
            reg_value[6] <= reg_value_nxt[6];
            reg_value[7] <= reg_value_nxt[7];
        end
    end

endmodule

software/smartfusion/hdl/stonyman_2_testbench/stonyman_controller_tb.v
////////////////////////////////////////////////////////////////////////////////
// Company: University of Michigan
//
// File: stonyman_conroller_tb.v
//
// Description:
//  TESTBENCH
//      Controller for the CentEye Stonyman imager.
//
// Targeted device: <Family::SmartFusion> <Die::A2F500M3G> <Package::484 FBGA>
// Author: Branden Ghena
//
//////////////////////////////////////////////////////////////////////////////// 

module stonyman_tb();
    reg clk;
    reg reset;
    reg frame_capture_start;
    reg adc_capture_done;

    reg [7:0] vsw_value;
    reg [7:0] hsw_value;
    reg [5:0] vref_value;
    reg [5:0] config_value;
    reg [5:0] nbias_value;
    reg [5:0] aobias_value;

    reg mask_capture_pixel;
    
    wire frame_capture_done;
    wire adc_capture_start;
    
    wire resp;
    wire incp;
    wire resv;
    wire incv;
    wire inphi;
    
    wire [6:0] mask_pixel_row;
    wire [6:0] mask_pixel_col;

    wire controller_busy;
    wire newline_sample;

    integer adc_count;

    stonyman uut (
        .clk                    (clk),
        .reset                  (reset),
        .frame_capture_start    (frame_capture_start),
        .adc_capture_done       (adc_capture_done),
        .vsw_value              (vsw_value),
        .hsw_value              (hsw_value),
        .vref_value             (vref_value),
        .config_value           (config_value),
        .nbias_value            (nbias_value),
        .aobias_value           (aobias_value),
        .mask_capture_pixel     (mask_capture_pixel),
        .frame_capture_done     (frame_capture_done),
        .adc_capture_start      (adc_capture_start),
        .resp                   (resp),
        .incp                   (incp),
        .resv                   (resv),
        .incv                   (incv),
        .inphi                  (inphi),
        .mask_pixel_row         (mask_pixel_row),
        .mask_pixel_col         (mask_pixel_col),
        .controller_busy        (controller_busy),
        .newline_sample         (newline_sample)
    );

    initial begin
        // creates data file for gtkwave
        $dumpfile("stonyman.vcd");
        $dumpvars(0, uut);
    end

    initial begin
        adc_count = 0;

        clk = 1;
        reset = 1;
        frame_capture_start = 0;
        adc_capture_done = 0;

        mask_capture_pixel = 1;

        vsw_value = 0;
        hsw_value = 0;
        vref_value = 41;
        config_value = 17;
        nbias_value = 50;
        aobias_value = 50;
    end

    always begin
        #5 clk = ~clk;
    end

    task SHOW_MODEL;
    begin
        $display ("[%d] [%d %d %d %d %d %d %d %d]",
                uut.ptr_value, uut.reg_value[0], uut.reg_value[1], uut.reg_value[2],
                uut.reg_value[3], uut.reg_value[4], uut.reg_value[5], uut.reg_value[6],
                uut.reg_value[7]);
    end
    endtask

    integer i;
    always @(posedge adc_capture_start) begin
        adc_count = adc_count+1;
        for (i=0; i<0+1; i=i+1) begin
            @(posedge clk);
        end
        adc_capture_done = 1;
        @(posedge clk);
        adc_capture_done = 0;
    end

    always @(posedge clk) begin
        $display ("\t%4d\t%b\t%b\t%b\t%b\t%b\t%d\t%d",
                $time, reset, resp, incp, resv, incv, uut.main_state, uut.sub_state);
    end

    initial begin
        $display ("\ttime\treset\tresp\tincp\tresv\tincv\tstate\tsub_state");
        #50;
        reset = 0;

        #4000;
        SHOW_MODEL();

        frame_capture_start = 1;
        #10;
        frame_capture_start = 0;

        @(negedge frame_capture_done);
        #1000;
        #12;
        SHOW_MODEL();
        $display("ADC Count: %d", adc_count);
        $finish;
    end

endmodule

software/smartfusion/stonyman.vcd
$date
	Fri Mar 25 14:45:43 2016
$end
$version
	ModelSim Version 10.3c
$end
$timescale
	1ns
$end

$scope module stonyman_tb $end

$scope module uut $end
$var wire 1 ! clk $end
$var wire 1 " reset $end
$var wire 1 # frame_capture_start $end
$var wire 1 $ adc_capture_done $end
$var wire 1 % vsw_value [7] $end
$var wire 1 & vsw_value [6] $end
$var wire 1 ' vsw_value [5] $end
$var wire 1 ( vsw_value [4] $end
$var wire 1 ) vsw_value [3] $end
$var wire 1 * vsw_value [2] $end
$var wire 1 + vsw_value [1] $end
$var wire 1 , vsw_value [0] $end
$var wire 1 - hsw_value [7] $end
$var wire 1 . hsw_value [6] $end
$var wire 1 / hsw_value [5] $end
$var wire 1 0 hsw_value [4] $end
$var wire 1 1 hsw_value [3] $end
$var wire 1 2 hsw_value [2] $end
$var wire 1 3 hsw_value [1] $end
$var wire 1 4 hsw_value [0] $end
$var wire 1 5 vref_value [5] $end
$var wire 1 6 vref_value [4] $end
$var wire 1 7 vref_value [3] $end
$var wire 1 8 vref_value [2] $end
$var wire 1 9 vref_value [1] $end
$var wire 1 : vref_value [0] $end
$var wire 1 ; config_value [5] $end
$var wire 1 < config_value [4] $end
$var wire 1 = config_value [3] $end
$var wire 1 > config_value [2] $end
$var wire 1 ? config_value [1] $end
$var wire 1 @ config_value [0] $end
$var wire 1 A nbias_value [5] $end
$var wire 1 B nbias_value [4] $end
$var wire 1 C nbias_value [3] $end
$var wire 1 D nbias_value [2] $end
$var wire 1 E nbias_value [1] $end
$var wire 1 F nbias_value [0] $end
$var wire 1 G aobias_value [5] $end
$var wire 1 H aobias_value [4] $end
$var wire 1 I aobias_value [3] $end
$var wire 1 J aobias_value [2] $end
$var wire 1 K aobias_value [1] $end
$var wire 1 L aobias_value [0] $end
$var wire 1 M mask_capture_pixel $end
$var reg 1 N controller_busy $end
$var reg 1 O frame_capture_done $end
$var reg 1 P adc_capture_start $end
$var reg 1 Q resp $end
$var reg 1 R incp $end
$var reg 1 S resv $end
$var reg 1 T incv $end
$var reg 1 U inphi $end
$var reg 7 V mask_pixel_row [6:0] $end
$var reg 7 W mask_pixel_col [6:0] $end
$var reg 1 X newline_sample $end
$var reg 4 Y main_state [3:0] $end
$var reg 4 Z main_state_nxt [3:0] $end
$var reg 4 [ sub_state [3:0] $end
$var reg 4 \ sub_state_nxt [3:0] $end
$var reg 1 ] pulse_pin_state [0:0] $end
$var reg 1 ^ pulse_pin_state_nxt [0:0] $end
$var reg 7 _ mask_pixel_row_nxt [6:0] $end
$var reg 7 ` mask_pixel_col_nxt [6:0] $end
$var reg 3 a ptr_value [2:0] $end
$var reg 3 b ptr_value_nxt [2:0] $end
$var reg 1 c frame_capture_done_nxt $end
$var reg 1 d adc_capture_start_nxt $end
$var reg 1 e resp_nxt $end
$var reg 1 f incp_nxt $end
$var reg 1 g resv_nxt $end
$var reg 1 h incv_nxt $end
$var reg 1 i inphi_nxt $end

$scope task SIGNAL_ERROR $end
$upscope $end

$scope task PULSE_PIN $end
$var reg 4 j cur_state [3:0] $end
$var reg 4 k new_state [3:0] $end
$var reg 4 l state_nxt [3:0] $end
$var reg 1 m pin $end
$upscope $end

$scope task RESET_PTR $end
$var reg 4 n cur_state [3:0] $end
$var reg 4 o new_state [3:0] $end
$var reg 4 p state_nxt [3:0] $end
$upscope $end

$scope task RESET_VAL $end
$var reg 4 q cur_state [3:0] $end
$var reg 4 r new_state [3:0] $end
$var reg 4 s state_nxt [3:0] $end
$upscope $end

$scope task INCR_PTR $end
$var reg 4 t cur_state [3:0] $end
$var reg 4 u new_state [3:0] $end
$var reg 4 v state_nxt [3:0] $end
$upscope $end

$scope task INCR_VAL $end
$var reg 4 w cur_state [3:0] $end
$var reg 4 x new_state [3:0] $end
$var reg 4 y state_nxt [3:0] $end
$upscope $end

$scope task SET_PTR $end
$var reg 3 z new_ptr_val [2:0] $end
$var reg 4 { cur_state [3:0] $end
$var reg 4 | new_state [3:0] $end
$var reg 4 } state_nxt [3:0] $end
$upscope $end

$scope task SET_VAL $end
$var reg 8 ~ new_reg_val [7:0] $end
$var reg 4 !! cur_state [3:0] $end
$var reg 4 "! new_state [3:0] $end
$var reg 4 #! state_nxt [3:0] $end
$upscope $end

$scope task GOTO_VAL $end
$var reg 8 $! new_reg_val [7:0] $end
$var reg 4 %! cur_state [3:0] $end
$var reg 4 &! new_state [3:0] $end
$var reg 4 '! state_nxt [3:0] $end
$upscope $end

$scope task NEXT_PIXEL $end
$upscope $end
$upscope $end
$upscope $end
$enddefinitions $end
#0
$dumpvars
1N
0O
0P
0Q
0R
0S
0T
0U
b0 V
b0 W
0X
b0 Y
b1 Z
b0 [
b0 \
b0 ]
b0 ^
b0 _
b0 `
b0 a
b0 b
0c
0d
0e
0f
0g
0h
0i
bx j
bx k
bx l
xm
bx n
bx o
bx p
bx q
bx r
bx s
bx t
bx u
bx v
bx w
bx x
bx y
bx z
bx {
bx |
bx }
bx ~
bx !!
bx "!
bx #!
bx $!
bx %!
bx &!
bx '!
1M
0L
1K
0J
0I
1H
1G
0F
1E
0D
0C
1B
1A
1@
0?
0>
0=
1<
0;
1:
09
08
17
06
15
04
03
02
01
00
0/
0.
0-
0,
0+
0*
0)
0(
0'
0&
0%
0$
0#
1"
1!
$end
#5
0!
#10
1!
#15
0!
#20
1!
#25
0!
#30
1!
#35
0!
#40
1!
#45
0!
#50
0"
1!
b1 Y
b1 n
b10 o
b1 j
b10 k
1m
b1 ^
b1 l
b1 p
1e
#55
0!
#60
1!
b1 ]
1Q
0e
0m
b0 ^
b10 l
b10 p
b10 Z
#65
0!
#70
1!
b10 Y
b0 ]
0Q
b0 z
b0 {
b1 |
b1 }
b1 \
#75
0!
#80
1!
b1 [
b10 q
b11 r
b10 j
b11 k
1m
b1 ^
b10 s
1g
#85
0!
#90
1!
b1 ]
1S
0g
0m
b0 ^
b11 l
b11 s
b11 Z
b0 \
#95
0!
#100
1!
b11 Y
b0 [
b0 ]
0S
b1 z
b0 t
b1 u
b0 j
b1 k
1m
b1 ^
b0 l
b0 v
1f
b0 }
#105
0!
#110
1!
b1 ]
1R
0f
0m
b0 ^
b1 l
b1 v
b1 b
b1 }
b1 \
#115
0!
#120
1!
b1 [
b0 ]
0R
b1 a
b11 q
b100 r
b11 j
b100 k
1m
b1 ^
b11 l
1g
#125
0!
#130
1!
b1 ]
1S
0g
0m
b0 ^
b100 l
b100 s
b100 Z
b0 \
#135
0!
#140
1!
b100 Y
b0 [
b0 ]
0S
b10 z
b0 j
b1 k
1m
b1 ^
b0 l
b0 v
1f
b0 }
#145
0!
#150
1!
b1 ]
1R
0f
0m
b0 ^
b1 l
b1 v
b10 b
b1 }
b1 \
#155
0!
#160
1!
b1 [
b0 ]
0R
b10 a
b1 q
b10 r
b1 j
b10 k
1m
b1 ^
b1 s
1g
#165
0!
#170
1!
b1 ]
1S
0g
0m
b0 ^
b10 l
b10 s
b10 \
#175
0!
#180
1!
b10 [
b0 ]
0S
b0 ~
b100 !!
b101 "!
b101 #!
b101 Z
b0 \
#185
0!
#190
1!
b101 Y
b0 [
b11 z
b0 j
b1 k
1m
b1 ^
b0 l
b0 v
1f
b0 }
#195
0!
#200
1!
b1 ]
1R
0f
0m
b0 ^
b1 l
b1 v
b11 b
b1 }
b1 \
#205
0!
#210
1!
b1 [
b0 ]
0R
b11 a
b1 j
b10 k
1m
b1 ^
b1 s
1g
#215
0!
#220
1!
b1 ]
1S
0g
0m
b0 ^
b10 l
b10 s
b10 \
#225
0!
#230
1!
b10 [
b0 ]
0S
b101 !!
b110 "!
b110 #!
b110 Z
b0 \
#235
0!
#240
1!
b110 Y
b0 [
b100 z
b0 j
b1 k
1m
b1 ^
b0 l
b0 v
1f
b0 }
#245
0!
#250
1!
b1 ]
1R
0f
0m
b0 ^
b1 l
b1 v
b100 b
b1 }
b1 \
#255
0!
#260
1!
b1 [
b0 ]
0R
b100 a
b1 j
b10 k
1m
b1 ^
b1 s
1g
#265
0!
#270
1!
b1 ]
1S
0g
0m
b0 ^
b10 l
b10 s
b10 \
#275
0!
#280
1!
b10 [
b0 ]
0S
b101001 ~
b110 !!
b111 "!
b110 w
b111 x
b110 j
b111 k
1m
b1 ^
b110 l
b110 y
1h
#285
0!
#290
1!
b1 ]
1T
0h
0m
b0 ^
b111 l
b111 y
b111 #!
b110 #!
#295
0!
#300
1!
b0 ]
0T
1m
b1 ^
b110 l
b110 y
1h
#305
0!
#310
1!
b1 ]
1T
0h
0m
b0 ^
b111 l
b111 y
b111 #!
b110 #!
#315
0!
#320
1!
b0 ]
0T
1m
b1 ^
b110 l
b110 y
1h
#325
0!
#330
1!
b1 ]
1T
0h
0m
b0 ^
b111 l
b111 y
b111 #!
b110 #!
#335
0!
#340
1!
b0 ]
0T
1m
b1 ^
b110 l
b110 y
1h
#345
0!
#350
1!
b1 ]
1T
0h
0m
b0 ^
b111 l
b111 y
b111 #!
b110 #!
#355
0!
#360
1!
b0 ]
0T
1m
b1 ^
b110 l
b110 y
1h
#365
0!
#370
1!
b1 ]
1T
0h
0m
b0 ^
b111 l
b111 y
b111 #!
b110 #!
#375
0!
#380
1!
b0 ]
0T
1m
b1 ^
b110 l
b110 y
1h
#385
0!
#390
1!
b1 ]
1T
0h
0m
b0 ^
b111 l
b111 y
b111 #!
b110 #!
#395
0!
#400
1!
b0 ]
0T
1m
b1 ^
b110 l
b110 y
1h
#405
0!
#410
1!
b1 ]
1T
0h
0m
b0 ^
b111 l
b111 y
b111 #!
b110 #!
#415
0!
#420
1!
b0 ]
0T
1m
b1 ^
b110 l
b110 y
1h
#425
0!
#430
1!
b1 ]
1T
0h
0m
b0 ^
b111 l
b111 y
b111 #!
b110 #!
#435
0!
#440
1!
b0 ]
0T
1m
b1 ^
b110 l
b110 y
1h
#445
0!
#450
1!
b1 ]
1T
0h
0m
b0 ^
b111 l
b111 y
b111 #!
b110 #!
#455
0!
#460
1!
b0 ]
0T
1m
b1 ^
b110 l
b110 y
1h
#465
0!
#470
1!
b1 ]
1T
0h
0m
b0 ^
b111 l
b111 y
b111 #!
b110 #!
#475
0!
#480
1!
b0 ]
0T
1m
b1 ^
b110 l
b110 y
1h
#485
0!
#490
1!
b1 ]
1T
0h
0m
b0 ^
b111 l
b111 y
b111 #!
b110 #!
#495
0!
#500
1!
b0 ]
0T
1m
b1 ^
b110 l
b110 y
1h
#505
0!
#510
1!
b1 ]
1T
0h
0m
b0 ^
b111 l
b111 y
b111 #!
b110 #!
#515
0!
#520
1!
b0 ]
0T
1m
b1 ^
b110 l
b110 y
1h
#525
0!
#530
1!
b1 ]
1T
0h
0m
b0 ^
b111 l
b111 y
b111 #!
b110 #!
#535
0!
#540
1!
b0 ]
0T
1m
b1 ^
b110 l
b110 y
1h
#545
0!
#550
1!
b1 ]
1T
0h
0m
b0 ^
b111 l
b111 y
b111 #!
b110 #!
#555
0!
#560
1!
b0 ]
0T
1m
b1 ^
b110 l
b110 y
1h
#565
0!
#570
1!
b1 ]
1T
0h
0m
b0 ^
b111 l
b111 y
b111 #!
b110 #!
#575
0!
#580
1!
b0 ]
0T
1m
b1 ^
b110 l
b110 y
1h
#585
0!
#590
1!
b1 ]
1T
0h
0m
b0 ^
b111 l
b111 y
b111 #!
b110 #!
#595
0!
#600
1!
b0 ]
0T
1m
b1 ^
b110 l
b110 y
1h
#605
0!
#610
1!
b1 ]
1T
0h
0m
b0 ^
b111 l
b111 y
b111 #!
b110 #!
#615
0!
